scorepdb/.ruff_cache/.gitignore
scorepdb/.ruff_cache/0.6.0/2206918975170337650
scorepdb/.ruff_cache/CACHEDIR.TAG
scorepdb/__init__.py
scorepdb/__main__.py
scorepdb/command_add.py
scorepdb/command_clear.py
scorepdb/command_download.py
scorepdb/command_get_id.py
scorepdb/command_health_check.py
scorepdb/command_merge.py
scorepdb/command_query.py
scorepdb/exceptions.py
scorepdb/main.py
scorepdb/object_store.py
scorepdb/rdf_database.py
scorepdb/rdf_helper.py
scorepdb-0.1.0.dist-info/LICENSE
scorepdb-0.1.0.dist-info/METADATA
scorepdb-0.1.0.dist-info/WHEEL
scorepdb-0.1.0.dist-info/entry_points.txt
scorepdb-0.1.0.dist-info/RECORD
