Metadata-Version: 2.1
Name: scorepdb
Version: 0.1.0
Summary: 
Author: Maximilian Sander
Author-email: maximilian.sander1@tu-dresden.de
Requires-Python: >=3.10,<4.0
Classifier: Programming Language :: Python :: 3
Classifier: Programming Language :: Python :: 3.10
Classifier: Programming Language :: Python :: 3.11
Classifier: Programming Language :: Python :: 3.12
Requires-Dist: minio (>=7.2.7,<8.0.0)
Requires-Dist: psycopg2-binary (>=2.9.9,<3.0.0)
Requires-Dist: python-dotenv (>=1.0.1,<2.0.0)
Requires-Dist: rdflib (>=7.0.0,<8.0.0)
Requires-Dist: rdflib-sqlalchemy (>=0.5.4,<0.6.0)
Requires-Dist: ruff (>=0.6.0,<0.7.0)
Requires-Dist: setuptools (>=72.2.0,<73.0.0)
